README.txt
setup.py
src/zif/__init__.py
src/zif.jsonserver.egg-info/PKG-INFO
src/zif.jsonserver.egg-info/SOURCES.txt
src/zif.jsonserver.egg-info/dependency_links.txt
src/zif.jsonserver.egg-info/namespace_packages.txt
src/zif.jsonserver.egg-info/not-zip-safe
src/zif.jsonserver.egg-info/requires.txt
src/zif.jsonserver.egg-info/top_level.txt
src/zif/jsonserver/CHANGES.txt
src/zif/jsonserver/DEPENDENCIES.cfg
src/zif/jsonserver/JSONViews.txt
src/zif/jsonserver/README.txt
src/zif/jsonserver/SETUP.cfg
src/zif/jsonserver/VERSION.txt
src/zif/jsonserver/ZopePublicLicense.txt
src/zif/jsonserver/__init__.py
src/zif/jsonserver/configure.zcml
src/zif/jsonserver/ftesting.py
src/zif/jsonserver/ftests.py
src/zif/jsonserver/interfaces.py
src/zif/jsonserver/jsoncomponent.py
src/zif/jsonserver/jsonrpc.py
src/zif/jsonserver/meta.zcml
src/zif/jsonserver/metaconfigure.py
src/zif/jsonserver/minjson.py
src/zif/jsonserver/requestpublicationfactory.py
src/zif/jsonserver/zif.jsonserver-configure.zcml
src/zif/jsonserver/zif.jsonserver-meta.zcml
src/zif/jsonserver/etc/zif.jsonserver-configure.zcml
src/zif/jsonserver/etc/zif.jsonserver-meta.zcml
src/zif/jsonserver/jsolait/README.txt
src/zif/jsonserver/jsolait/init.js
src/zif/jsonserver/jsolait/install_jsolait.py
src/zif/jsonserver/jsolait/jsolait.js
src/zif/jsonserver/jsolait/jsolait.wsf
src/zif/jsonserver/jsolait/doc/LICENSE.txt
src/zif/jsonserver/jsolait/lib/codecs.js
src/zif/jsonserver/jsolait/lib/crypto.js
src/zif/jsonserver/jsolait/lib/dom.js
src/zif/jsonserver/jsolait/lib/forms.js
src/zif/jsonserver/jsolait/lib/iter.js
src/zif/jsonserver/jsolait/lib/jsonrpc.js
src/zif/jsonserver/jsolait/lib/lang.js
src/zif/jsonserver/jsolait/lib/pythonkw.js
src/zif/jsonserver/jsolait/lib/sets.js
src/zif/jsonserver/jsolait/lib/testing.js
src/zif/jsonserver/jsolait/lib/urllib.js
src/zif/jsonserver/jsolait/lib/xml.js
src/zif/jsonserver/jsolait/lib/xmlrpc.js
src/zif/jsonserver/jsolait/src/VERSION.txt
src/zif/jsonserver/tests/__init__.py
src/zif/jsonserver/tests/jsonrpc.zcml
src/zif/jsonserver/tests/jsonrpc_error.zcml
src/zif/jsonserver/tests/jsonrpcviews.py
src/zif/jsonserver/tests/test.pt
src/zif/jsonserver/tests/test_directives.py
src/zif/jsonserver/tests/test_httpfactory.py
src/zif/jsonserver/tests/test_json.py
