Metadata-Version: 1.0
Name: zif.jsonserver
Version: 0.6
Summary: A json server for zope 3.
Home-page: http://zif.svn.sourceforge.net/viewvc/zif/zif.jsonserver
Author: Jim Washington and contributors
Author-email: jwashin@users.sourceforge.net
License: ZPL2.1 and LGPL
Keywords: jsonserver json zope3
Platform: UNKNOWN
Classifier: Framework :: Buildout
Classifier: Framework :: Zope3
Classifier: Intended Audience :: Developers
Classifier: Development Status :: 5 - Production/Stable
Classifier: Environment :: Web Environment
Classifier: License :: OSI Approved :: Zope Public License
Classifier: License :: OSI Approved :: GNU Library or Lesser General Public License (LGPL)
Classifier: Operating System :: OS Independent
Classifier: Programming Language :: Python
Classifier: Topic :: Software Development :: Libraries :: Python Modules
